lugatim_cli/__init__.py
lugatim_cli/__main__.py
lugatim_cli/cli.py
lugatim_cli-0.0.1.dist-info/METADATA
lugatim_cli-0.0.1.dist-info/WHEEL
lugatim_cli-0.0.1.dist-info/entry_points.txt
lugatim_cli-0.0.1.dist-info/top_level.txt
lugatim_cli-0.0.1.dist-info/RECORD
