Metadata-Version: 2.1
Name: lugatim-cli
Version: 0.0.1
Summary: Command-line tool for Kubbealti Lugati, lugatim.com with rich output.
Home-page: https://github.com/agmmnn/lugatim-cli
Author: agmmnn
License: UNKNOWN
Platform: UNKNOWN
Classifier: Programming Language :: Python :: 3
Classifier: Operating System :: OS Independent
Classifier: Environment :: Console
Classifier: Topic :: Utilities
Requires-Python: >=3.5
Requires-Dist: rich
Requires-Dist: requests
Requires-Dist: beautifulsoup4
Requires-Dist: lxml
